piffle/__init__.py
piffle/image.py
piffle/presentation.py
piffle-0.6.1.dist-info/METADATA
piffle-0.6.1.dist-info/WHEEL
piffle-0.6.1.dist-info/licenses/LICENSE
piffle-0.6.1.dist-info/RECORD
