Metadata-Version: 2.4
Name: piffle
Version: 0.6.1
Summary: Python library for working with IIIF Image and Presentation APIs
Project-URL: Homepage, https://github.com/princeton-cdh/piffle
Project-URL: Repository, https://github.com/princeton-cdh/piffle
Project-URL: Changelog, https://github.com/Princeton-CDH/piffle/blob/main/README.md
Author-email: The Center for Digital Humanities at Princeton <cdhdevteam@princeton.edu>
License: Apache License, Version 2.0
License-File: LICENSE
Keywords: iiif
Classifier: Development Status :: 4 - Beta
Classifier: Intended Audience :: Developers
Classifier: License :: OSI Approved :: Apache Software License
Classifier: Natural Language :: English
Classifier: Operating System :: OS Independent
Classifier: Programming Language :: Python
Classifier: Programming Language :: Python :: 3
Classifier: Programming Language :: Python :: 3.8
Classifier: Programming Language :: Python :: 3.9
Classifier: Programming Language :: Python :: 3.10
Classifier: Programming Language :: Python :: 3.11
Classifier: Programming Language :: Python :: 3.12
Classifier: Programming Language :: Python :: 3.13
Classifier: Topic :: Software Development :: Libraries :: Python Modules
Requires-Python: >=3.8
Requires-Dist: addict
Requires-Dist: cached-property
Requires-Dist: requests
Provides-Extra: dev
Requires-Dist: pre-commit; extra == 'dev'
Requires-Dist: pytest-cov; extra == 'dev'
Requires-Dist: pytest>=3.6; extra == 'dev'
Provides-Extra: test
Requires-Dist: pytest-cov; extra == 'test'
Requires-Dist: pytest>=3.6; extra == 'test'
